setup.py
src/digimat/__init__.py
src/digimat.gmail.egg-info/PKG-INFO
src/digimat.gmail.egg-info/SOURCES.txt
src/digimat.gmail.egg-info/dependency_links.txt
src/digimat.gmail.egg-info/namespace_packages.txt
src/digimat.gmail.egg-info/not-zip-safe
src/digimat.gmail.egg-info/requires.txt
src/digimat.gmail.egg-info/top_level.txt
src/digimat/gmail/__init__.py
src/digimat/gmail/gmail.py