Metadata-Version: 1.0
Name: digimat.gmail
Version: 0.1.0
Summary: Digimat Google Mail sender
Home-page: UNKNOWN
Author: Frederic Hess
Author-email: fhess@splust.ch
License: PSF
Platform: UNKNOWN
